[
  {
    "id": "1",
    "nome": "Piemonte",
    "latitudine": 45.066667,
    "longitudine": 7.700000,
    "flag":"https://upload.wikimedia.org/wikipedia/commons/4/42/Regione-Piemonte-Stemma.svg"    
  },
  {
    "id": "2",
    "nome": "Valle d'Aosta/Vallée d'Aoste",
    "latitudine": 45.737222,
    "longitudine": 7.320556,
    "flag":"https://upload.wikimedia.org/wikipedia/commons/f/f6/Valle_d%27Aosta-Stemma.svg"      
  },
  {
    "id": "3",
    "nome": "Lombardia",
    "latitudine": 45.464161,
    "longitudine": 9.190336,
    "flag":"https://upload.wikimedia.org/wikipedia/commons/1/12/Regione-Lombardia-Stemma.svg"
  },
  {
    "id": "4",
    "nome": "Trentino-Alto Adige/Südtirol",
    "latitudine": 46.066667,
    "longitudine": 11.116667,
    "flag":"https://upload.wikimedia.org/wikipedia/commons/b/b4/Coat_of_arms_of_Trentino-South_Tyrol.svg"
  },
  {
    "id": "5",
    "nome": "Veneto",
    "latitudine": 45.439722,
    "longitudine": 12.331944,
    "flag":"https://upload.wikimedia.org/wikipedia/commons/c/cd/Coat_of_Arms_of_Veneto.png"
  },
  {
    "id": "6",
    "nome": "Friuli-Venezia Giulia",
    "latitudine": 45.636111,
    "longitudine": 13.804167,
    "flag":"https://upload.wikimedia.org/wikipedia/commons/c/c3/Friuli-Venezia-Giulia-Stemma.svg"
  },
  {
    "id": "7",
    "nome": "Liguria",
    "latitudine": 44.411156,
    "longitudine": 8.932661,
    "flag":"https://upload.wikimedia.org/wikipedia/commons/4/41/Coat_of_arms_of_Liguria.svg"
  },
  {
    "id": "8",
    "nome": "Emilia-Romagna",
    "latitudine": 44.493889,
    "longitudine": 11.342778,
    "flag":"https://upload.wikimedia.org/wikipedia/commons/c/ca/Regione-Emilia-Romagna-Stemma.svg"
  },
  {
    "id": "9",
    "nome": "Toscana",
    "latitudine": 43.771389,
    "longitudine": 11.254167,
    "flag":"https://upload.wikimedia.org/wikipedia/commons/4/4f/Coat_of_arms_of_Tuscany.svg"
  },
  {
    "id": "10",
    "nome": "Umbria",
    "latitudine": 43.112100,
    "longitudine": 12.388800,
    "flag":"https://upload.wikimedia.org/wikipedia/commons/5/55/Regione-Umbria-Stemma.svg"
  }, 
  {
    "id": "11",
    "nome": "Marche",
    "latitudine": 43.616667,
    "longitudine": 13.516667,
    "flag":"https://upload.wikimedia.org/wikipedia/commons/b/b9/Coat_of_arms_of_Marche.svg"
  },
  {
    "id": "12",
    "nome": "Lazio",
    "latitudine": 41.893056,
    "longitudine": 12.482778,
    "flag":"https://upload.wikimedia.org/wikipedia/commons/7/76/Lazio_Coat_of_Arms.svg"    
  },
  {
    "id": "13",
    "nome": "Abruzzo",
    "latitudine": 42.354008,
    "longitudine": 13.391992,
    "flag":"https://upload.wikimedia.org/wikipedia/commons/c/ce/Regione-Abruzzo-Stemma.svg"
  },
  {
    "id": "14",
    "nome": "Molise",
    "latitudine": 41.561000,
    "longitudine": 14.668400,
    "flag":"https://upload.wikimedia.org/wikipedia/commons/f/fb/Regione-Molise-Stemma.svg"
  },
  {
    "id": "15",
    "nome": "Campania",
    "latitudine": 40.833333,
    "longitudine": 14.250000,
    "flag":"https://upload.wikimedia.org/wikipedia/commons/a/a8/Regione-Campania-Stemma.svg"
  },
  {
    "id": "16",
    "nome": "Puglia",
    "latitudine": 41.125278,
    "longitudine": 16.866667,
    "flag":"https://upload.wikimedia.org/wikipedia/commons/d/d0/Coat_of_Arms_of_Apulia.svg"
  },
  {
    "id": "17",
    "nome": "Basilicata",
    "latitudine": 40.633333,
    "longitudine": 15.800000,
    "flag":"https://upload.wikimedia.org/wikipedia/commons/0/07/Regione-Basilicata-Stemma.svg"
  },
  {
    "id": "19",
    "nome": "Sicilia",
    "latitudine": 38.115556,
    "longitudine": 13.361389,
    "flag":"https://upload.wikimedia.org/wikipedia/commons/d/df/Coat_of_arms_of_Sicily.svg"
  },
  {
    "id": "18",
    "nome": "Calabria",
    "latitudine": 38.910000,
    "longitudine": 16.587500,
    "flag":"https://upload.wikimedia.org/wikipedia/commons/b/bf/Coat_of_arms_of_Calabria.svg"
  },
  {
    "id": "20",
    "nome": "Sardegna",
    "latitudine": 39.216667,
    "longitudine": 9.116667,
    "flag":"https://upload.wikimedia.org/wikipedia/commons/3/33/Sardegna-Stemma.svg"
  }
]